LICENSE.txt
PanChIP_manual.pdf
README.md
setup.cfg
setup.py
PanChIP/__init__.py
PanChIP/analysis.sh
PanChIP/commands.py
PanChIP/filter.sh
PanChIP/version.py
bin/panchip
lib/cellLine.tsv
panchip.egg-info/PKG-INFO
panchip.egg-info/SOURCES.txt
panchip.egg-info/dependency_links.txt
panchip.egg-info/requires.txt
panchip.egg-info/top_level.txt