Metadata-Version: 2.1
Name: panchip
Version: 3.0.13
Summary: Pan-ChIP-seq Analysis of Peak Sets
Home-page: https://github.com/hanjunlee21/PanChIP
Author: Hanjun Lee
Author-email: hanjun@alum.mit.edu
License: MIT
Download-URL: https://github.com/hanjunlee21/PanChIP/archive/refs/tags/v.3.0.13.tar.gz
Keywords: chip-seq,bedfile
Platform: UNKNOWN
Classifier: Development Status :: 5 - Production/Stable
Classifier: Intended Audience :: Science/Research
Classifier: Topic :: Scientific/Engineering :: Bio-Informatics
Classifier: License :: OSI Approved :: MIT License
Classifier: Programming Language :: Python :: 3
Classifier: Programming Language :: Python :: 3.0
Classifier: Programming Language :: Python :: 3.1
Classifier: Programming Language :: Python :: 3.2
Classifier: Programming Language :: Python :: 3.3
Classifier: Programming Language :: Python :: 3.4
Classifier: Programming Language :: Python :: 3.5
Classifier: Programming Language :: Python :: 3.6
Classifier: Programming Language :: Awk
Classifier: Programming Language :: Unix Shell
